huscy/consents/__init__.py
huscy/consents/admin.py
huscy/consents/apps.py
huscy/consents/forms.py
huscy/consents/models.py
huscy/consents/services.py
huscy/consents/urls.py
huscy/consents/views.py
huscy/consents/migrations/0001_initial.py
huscy/consents/migrations/__init__.py
huscy/consents/static/consents/css/fomantic.min.css
huscy/consents/static/consents/css/fomantic2.9.0.min.css
huscy/consents/static/consents/img/logo.svg
huscy/consents/static/consents/js/fomantic.min.js
huscy/consents/static/consents/js/fomantic2.9.0.min.js
huscy/consents/static/consents/js/jquery.min.js
huscy/consents/static/consents/js/jquery3.6.1.min.js
huscy/consents/static/consents/js/popper.min.js
huscy/consents/static/consents/js/popper1.16.1.min.js
huscy/consents/templates/consents/base.html
huscy/consents/templates/consents/create_consent.html
huscy/consents/templates/consents/sign_consent.html
huscy/consents/templates/consents/signed_consent.html
huscy/consents/templates/consents/success.html
huscy/consents/templates/consents/text_fragments/checkbox.html
huscy/consents/templates/consents/text_fragments/heading.html
huscy/consents/templates/consents/text_fragments/markdown.html
huscy/consents/templates/consents/text_fragments/page-break.html
huscy/consents/templates/consents/text_fragments/paragraph.html
huscy/consents/templates/consents/widgets/select_date.html
huscy/consents/templatetags/__init__.py
huscy/consents/templatetags/dict_extras.py
huscy.consents-0.9.0a23.dist-info/LICENSE
huscy.consents-0.9.0a23.dist-info/METADATA
huscy.consents-0.9.0a23.dist-info/WHEEL
huscy.consents-0.9.0a23.dist-info/top_level.txt
huscy.consents-0.9.0a23.dist-info/RECORD
